odoo/addons/project_list/README.rst
odoo/addons/project_list/__init__.py
odoo/addons/project_list/__manifest__.py
odoo/addons/project_list/i18n/de.po
odoo/addons/project_list/i18n/project_list.pot
odoo/addons/project_list/readme/CONTRIBUTORS.rst
odoo/addons/project_list/readme/DESCRIPTION.rst
odoo/addons/project_list/static/description/icon.png
odoo/addons/project_list/static/description/index.html
odoo/addons/project_list/views/project_project.xml
odoo11_addon_project_list-11.0.1.0.0.99.dev4.dist-info/METADATA
odoo11_addon_project_list-11.0.1.0.0.99.dev4.dist-info/WHEEL
odoo11_addon_project_list-11.0.1.0.0.99.dev4.dist-info/top_level.txt
odoo11_addon_project_list-11.0.1.0.0.99.dev4.dist-info/RECORD
